{
  "variants": {
    "facing=down": {
      "model": "futurefood:block/quantum_energy_diffuser",
      "x": 180
    },
    "facing=east": {
      "model": "futurefood:block/quantum_energy_diffuser",
      "x": 90,
      "y": 90
    },
    "facing=north": {
      "model": "futurefood:block/quantum_energy_diffuser",
      "x": 90
    },
    "facing=south": {
      "model": "futurefood:block/quantum_energy_diffuser",
      "x": 90,
      "y": 180
    },
    "facing=up": {
      "model": "futurefood:block/quantum_energy_diffuser"
    },
    "facing=west": {
      "model": "futurefood:block/quantum_energy_diffuser",
      "x": 90,
      "y": 270
    }
  },
  "multipart": [
    {
      "when": {
        "AND": [
          {
            "acing": "down"
          }
        ]
      },
      "apply": [
      ]
    },
    {
      "when": {
        "AND": [
          {
            "acing": "east"
          }
        ]
      },
      "apply": [
      ]
    },
    {
      "when": {
        "AND": [
          {
            "acing": "north"
          }
        ]
      },
      "apply": [
      ]
    },
    {
      "when": {
        "AND": [
          {
            "acing": "south"
          }
        ]
      },
      "apply": [
      ]
    },
    {
      "when": {
        "AND": [
          {
            "acing": "up"
          }
        ]
      },
      "apply": [
      ]
    },
    {
      "when": {
        "AND": [
          {
            "acing": "west"
          }
        ]
      },
      "apply": [
      ]
    }
  ]
}
