{
  "format_version": "1.9.0",
  "credit": "Made with Blockbench",
  "parent": "minecraft:block/cube_all",
  "render_type": "minecraft:cutout",
  "texture_size": [
    128,
    128
  ],
  "textures": {
    "1": "futurefood:block/battery",
    "particle": "futurefood:block/particle"
  },
  "elements": [
    {
      "from": [
        0,
        0,
        0
      ],
      "to": [
        16,
        2,
        16
      ],
      "rotation": {
        "angle": 0,
        "axis": "y",
        "origin": [
          8,
          8,
          8
        ]
      },
      "faces": {
        "north": {
          "uv": [
            7.875,
            4.375,
            9.875,
            4.625
          ],
          "texture": "#1"
        },
        "east": {
          "uv": [
            7.875,
            4.75,
            9.875,
            5
          ],
          "texture": "#1"
        },
        "south": {
          "uv": [
            7.875,
            5.125,
            9.875,
            5.375
          ],
          "texture": "#1"
        },
        "west": {
          "uv": [
            8.625,
            2.625,
            10.625,
            2.875
          ],
          "texture": "#1"
        },
        "up": {
          "uv": [
            2,
            2,
            0,
            0
          ],
          "texture": "#1"
        },
        "down": {
          "uv": [
            2,
            2.125,
            0,
            4.125
          ],
          "texture": "#1"
        }
      }
    },
    {
      "from": [
        13,
        2,
        0
      ],
      "to": [
        16,
        13,
        3
      ],
      "rotation": {
        "angle": 0,
        "axis": "y",
        "origin": [
          8,
          8,
          8
        ]
      },
      "faces": {
        "north": {
          "uv": [
            8.125,
            2.375,
            8.5,
            3.75
          ],
          "texture": "#1"
        },
        "east": {
          "uv": [
            1.125,
            8.25,
            1.5,
            9.625
          ],
          "texture": "#1"
        },
        "south": {
          "uv": [
            1.625,
            8.25,
            2,
            9.625
          ],
          "texture": "#1"
        },
        "west": {
          "uv": [
            2.125,
            8.25,
            2.5,
            9.625
          ],
          "texture": "#1"
        },
        "up": {
          "uv": [
            4.125,
            4.625,
            3.75,
            4.25
          ],
          "texture": "#1"
        },
        "down": {
          "uv": [
            3.125,
            5.875,
            2.75,
            6.25
          ],
          "texture": "#1"
        }
      }
    },
    {
      "from": [
        0,
        2,
        0
      ],
      "to": [
        3,
        13,
        3
      ],
      "rotation": {
        "angle": 0,
        "axis": "y",
        "origin": [
          8,
          8,
          8
        ]
      },
      "faces": {
        "north": {
          "uv": [
            7.5,
            8.25,
            7.875,
            9.625
          ],
          "texture": "#1"
        },
        "east": {
          "uv": [
            8,
            8.25,
            8.375,
            9.625
          ],
          "texture": "#1"
        },
        "south": {
          "uv": [
            0,
            8.5,
            0.375,
            9.875
          ],
          "texture": "#1"
        },
        "west": {
          "uv": [
            0.5,
            8.5,
            0.875,
            9.875
          ],
          "texture": "#1"
        },
        "up": {
          "uv": [
            3.625,
            6.25,
            3.25,
            5.875
          ],
          "texture": "#1"
        },
        "down": {
          "uv": [
            5.125,
            9.375,
            4.75,
            9.75
          ],
          "texture": "#1"
        }
      }
    },
    {
      "from": [
        0,
        2,
        13
      ],
      "to": [
        16,
        13,
        16
      ],
      "rotation": {
        "angle": 0,
        "axis": "y",
        "origin": [
          8,
          8,
          8
        ]
      },
      "faces": {
        "north": {
          "uv": [
            0,
            4.25,
            2,
            5.625
          ],
          "texture": "#1"
        },
        "east": {
          "uv": [
            8.5,
            8.25,
            8.875,
            9.625
          ],
          "texture": "#1"
        },
        "south": {
          "uv": [
            4.25,
            0,
            6.25,
            1.375
          ],
          "texture": "#1"
        },
        "west": {
          "uv": [
            8.625,
            1.125,
            9,
            2.5
          ],
          "texture": "#1"
        },
        "up": {
          "uv": [
            9,
            4.25,
            7,
            3.875
          ],
          "texture": "#1"
        },
        "down": {
          "uv": [
            9.5,
            7.75,
            7.5,
            8.125
          ],
          "texture": "#1"
        }
      }
    },
    {
      "from": [
        0,
        13,
        0
      ],
      "to": [
        16,
        15,
        16
      ],
      "rotation": {
        "angle": 0,
        "axis": "y",
        "origin": [
          8,
          8,
          8
        ]
      },
      "faces": {
        "north": {
          "uv": [
            8.625,
            3,
            10.625,
            3.25
          ],
          "texture": "#1"
        },
        "east": {
          "uv": [
            8.625,
            3.375,
            10.625,
            3.625
          ],
          "texture": "#1"
        },
        "south": {
          "uv": [
            4.875,
            8.625,
            6.875,
            8.875
          ],
          "texture": "#1"
        },
        "west": {
          "uv": [
            8.625,
            5.5,
            10.625,
            5.75
          ],
          "texture": "#1"
        },
        "up": {
          "uv": [
            4.125,
            2,
            2.125,
            0
          ],
          "texture": "#1"
        },
        "down": {
          "uv": [
            4.125,
            2.125,
            2.125,
            4.125
          ],
          "texture": "#1"
        }
      }
    },
    {
      "from": [
        4,
        14,
        4
      ],
      "to": [
        12,
        16,
        12
      ],
      "rotation": {
        "angle": 0,
        "axis": "y",
        "origin": [
          8,
          8,
          8
        ]
      },
      "faces": {
        "north": {
          "uv": [
            5.875,
            2.75,
            6.875,
            3
          ],
          "texture": "#1"
        },
        "east": {
          "uv": [
            8.625,
            7.375,
            9.625,
            7.625
          ],
          "texture": "#1"
        },
        "south": {
          "uv": [
            8.75,
            0.75,
            9.75,
            1
          ],
          "texture": "#1"
        },
        "west": {
          "uv": [
            4.125,
            9,
            5.125,
            9.25
          ],
          "texture": "#1"
        },
        "up": {
          "uv": [
            6.25,
            7.375,
            5.25,
            6.375
          ],
          "texture": "#1"
        },
        "down": {
          "uv": [
            7.375,
            6.375,
            6.375,
            7.375
          ],
          "texture": "#1"
        }
      }
    },
    {
      "from": [
        1.49,
        1.49,
        0.49
      ],
      "to": [
        13.51,
        13.51,
        0.51
      ],
      "rotation": {
        "angle": 0,
        "axis": "y",
        "origin": [
          8,
          8,
          8
        ]
      },
      "faces": {
        "north": {
          "uv": [
            4.25,
            1.5,
            5.75,
            3
          ],
          "texture": "#1"
        },
        "east": {
          "uv": [
            1,
            8.5,
            1,
            10
          ],
          "texture": "#1"
        },
        "south": {
          "uv": [
            2.125,
            4.25,
            3.625,
            5.75
          ],
          "texture": "#1"
        },
        "west": {
          "uv": [
            7.125,
            8.625,
            7.125,
            10.125
          ],
          "texture": "#1"
        },
        "up": {
          "uv": [
            10.625,
            2.375,
            9.125,
            2.375
          ],
          "texture": "#1"
        },
        "down": {
          "uv": [
            10.625,
            2.5,
            9.125,
            2.5
          ],
          "texture": "#1"
        }
      }
    },
    {
      "from": [
        15.49,
        1.49,
        2.49
      ],
      "to": [
        15.51,
        13.51,
        13.51
      ],
      "rotation": {
        "angle": 0,
        "axis": "y",
        "origin": [
          8,
          8,
          8
        ]
      },
      "faces": {
        "north": {
          "uv": [
            7.25,
            8.625,
            7.25,
            10.125
          ],
          "texture": "#1"
        },
        "east": {
          "uv": [
            4.25,
            3.125,
            5.625,
            4.625
          ],
          "texture": "#1"
        },
        "south": {
          "uv": [
            7.375,
            8.625,
            7.375,
            10.125
          ],
          "texture": "#1"
        },
        "west": {
          "uv": [
            3.75,
            4.75,
            5.125,
            6.25
          ],
          "texture": "#1"
        },
        "up": {
          "uv": [
            2.625,
            10.875,
            2.625,
            9.5
          ],
          "texture": "#1"
        },
        "down": {
          "uv": [
            2.75,
            9.5,
            2.75,
            10.875
          ],
          "texture": "#1"
        }
      }
    },
    {
      "from": [
        0.49,
        1.49,
        2.49
      ],
      "to": [
        0.51,
        13.51,
        13.51
      ],
      "rotation": {
        "angle": 0,
        "axis": "y",
        "origin": [
          8,
          8,
          8
        ]
      },
      "faces": {
        "north": {
          "uv": [
            2.875,
            9.5,
            2.875,
            11
          ],
          "texture": "#1"
        },
        "east": {
          "uv": [
            5.25,
            4.75,
            6.625,
            6.25
          ],
          "texture": "#1"
        },
        "south": {
          "uv": [
            3,
            9.5,
            3,
            11
          ],
          "texture": "#1"
        },
        "west": {
          "uv": [
            0,
            5.75,
            1.375,
            7.25
          ],
          "texture": "#1"
        },
        "up": {
          "uv": [
            3.125,
            10.875,
            3.125,
            9.5
          ],
          "texture": "#1"
        },
        "down": {
          "uv": [
            3.25,
            9.5,
            3.25,
            10.875
          ],
          "texture": "#1"
        }
      }
    }
  ],
  "groups": [
    {
      "name": "Battery",
      "origin": [
        8,
        8,
        8
      ],
      "color": 0,
      "children": [
        0,
        1,
        2,
        3,
        4,
        5,
        6,
        7,
        8
      ]
    }
  ]
}
